<annotation>
    <folder>yolo2voc</folder>
    <filename>driving-night-tokyo_000195_jpg.rf.7994d3f34f9ddf186c00896292be4333.xml</filename>
    <path>D:\DatasetsCHA\FormatConverter\yolo2voc\driving-night-tokyo_000195_jpg.rf.7994d3f34f9ddf186c00896292be4333.xml</path>
    <source>
        <database>Unknown</database>
    </source>
    <size>
        <width>1280</width>
        <height>720</height>
        <depth>3</depth>
    </size>
    <segmented>0</segmented>
    <object>
        <name>car</name>
        <pose>Unspecified</pose>
        <truncated>0</truncated>
        <difficult>0</difficult>
        <bndbox>
            <xmin>583</xmin>
            <ymin>456</ymin>
            <xmax>605</xmax>
            <ymax>474</ymax>
        </bndbox>
    </object>    <object>
        <name>traffic light</name>
        <pose>Unspecified</pose>
        <truncated>0</truncated>
        <difficult>0</difficult>
        <bndbox>
            <xmin>144</xmin>
            <ymin>362</ymin>
            <xmax>179</xmax>
            <ymax>394</ymax>
        </bndbox>
    </object>    <object>
        <name>car</name>
        <pose>Unspecified</pose>
        <truncated>0</truncated>
        <difficult>0</difficult>
        <bndbox>
            <xmin>616</xmin>
            <ymin>465</ymin>
            <xmax>636</xmax>
            <ymax>478</ymax>
        </bndbox>
    </object>    <object>
        <name>car</name>
        <pose>Unspecified</pose>
        <truncated>0</truncated>
        <difficult>0</difficult>
        <bndbox>
            <xmin>517</xmin>
            <ymin>460</ymin>
            <xmax>544</xmax>
            <ymax>478</ymax>
        </bndbox>
    </object>    <object>
        <name>car</name>
        <pose>Unspecified</pose>
        <truncated>0</truncated>
        <difficult>0</difficult>
        <bndbox>
            <xmin>676</xmin>
            <ymin>451</ymin>
            <xmax>728</xmax>
            <ymax>495</ymax>
        </bndbox>
    </object>
</annotation>
